odoo/addons/stock_picking_report_undelivered_product/README.rst
odoo/addons/stock_picking_report_undelivered_product/__init__.py
odoo/addons/stock_picking_report_undelivered_product/__manifest__.py
odoo/addons/stock_picking_report_undelivered_product/i18n/es.po
odoo/addons/stock_picking_report_undelivered_product/i18n/stock_picking_report_undelivered_product.pot
odoo/addons/stock_picking_report_undelivered_product/models/__init__.py
odoo/addons/stock_picking_report_undelivered_product/models/product_template.py
odoo/addons/stock_picking_report_undelivered_product/models/res_config_settings.py
odoo/addons/stock_picking_report_undelivered_product/models/res_partner.py
odoo/addons/stock_picking_report_undelivered_product/models/stock_move.py
odoo/addons/stock_picking_report_undelivered_product/readme/CONTRIBUTORS.rst
odoo/addons/stock_picking_report_undelivered_product/readme/DESCRIPTION.rst
odoo/addons/stock_picking_report_undelivered_product/readme/USAGE.rst
odoo/addons/stock_picking_report_undelivered_product/static/description/icon.png
odoo/addons/stock_picking_report_undelivered_product/static/description/index.html
odoo/addons/stock_picking_report_undelivered_product/tests/__init__.py
odoo/addons/stock_picking_report_undelivered_product/tests/test_stock_picking_report_undelivered_product.py
odoo/addons/stock_picking_report_undelivered_product/views/product_views.xml
odoo/addons/stock_picking_report_undelivered_product/views/report_deliveryslip.xml
odoo/addons/stock_picking_report_undelivered_product/views/res_config_settings_views.xml
odoo/addons/stock_picking_report_undelivered_product/views/res_partner_view.xml
odoo13_addon_stock_picking_report_undelivered_product-13.0.1.0.1.dev3.dist-info/METADATA
odoo13_addon_stock_picking_report_undelivered_product-13.0.1.0.1.dev3.dist-info/WHEEL
odoo13_addon_stock_picking_report_undelivered_product-13.0.1.0.1.dev3.dist-info/top_level.txt
odoo13_addon_stock_picking_report_undelivered_product-13.0.1.0.1.dev3.dist-info/RECORD
